{
  "_class": "group",
  "do_objectID": "70BC75BF-4F56-410C-ACC5-5E9E13A014E9",
  "exportOptions": {
    "_class": "exportOptions",
    "exportFormats": [
    ],
    "includedLayerIds": [
    ],
    "layerOptions": 0,
    "shouldTrim": false
  },
  "frame": {
    "_class": "rect",
    "constrainProportions": false,
    "height": 380,
    "width": 1131,
    "x": 0,
    "y": 1744
  },
  "hasClickThrough": true,
  "isFlippedHorizontal": false,
  "isFlippedVertical": false,
  "isLocked": false,
  "isVisible": true,
  "layerListExpandedType": 0,
  "layers": [
    {
      "class": "symbolInstance",
      "id": "F6EDEB68-7B04-4868-A649-795DA6030906"
    },
    {
      "class": "text",
      "id": "D9C9607E-6810-4591-B9E3-59087156C8B7"
    },
    {
      "class": "symbolInstance",
      "id": "C3F6691F-1E66-48DC-9243-6F4DD8EA4BC0"
    },
    {
      "class": "text",
      "id": "916BB4DD-B430-468B-8971-C59BFEF24781"
    },
    {
      "class": "symbolInstance",
      "id": "16724411-2346-42E3-88CF-CB816B949537"
    },
    {
      "class": "text",
      "id": "4471D9C8-F5A4-45DF-8BE7-DA84C15F1C3B"
    },
    {
      "class": "symbolInstance",
      "id": "C2631A42-48B7-4D3B-B6EC-26C27D16C70C"
    },
    {
      "class": "text",
      "id": "20E3D2A1-A9F0-4031-BC30-84B0C5BA39CC"
    },
    {
      "class": "text",
      "id": "C55536E4-BF0C-4EF7-ABAE-AC742B7423FC"
    }
  ],
  "name": "Alerts",
  "nameIsFixed": true,
  "resizingConstraint": 63,
  "resizingType": 0,
  "rotation": 0,
  "shouldBreakMaskChain": false,
  "style": {
    "_class": "style",
    "endDecorationType": 0,
    "miterLimit": 10,
    "startDecorationType": 0
  }
}